cascade/__init__.py
cascade/chat/__init__.py
cascade/chat/completions.py
cascade/strategies/__init__.py
cascade/strategies/base.py
cascade/strategies/remote_semantic.py
cascade/strategies/semantic.py
cascade/strategies/strict.py
cascade_inference-0.1.1.dist-info/licenses/LICENSE
cascade_inference-0.1.1.dist-info/METADATA
cascade_inference-0.1.1.dist-info/WHEEL
cascade_inference-0.1.1.dist-info/top_level.txt
cascade_inference-0.1.1.dist-info/RECORD
