Metadata-Version: 2.4
Name: cascade-inference
Version: 0.1.1
Summary: Cascade based inference for large language models.
Home-page: https://github.com/elibutters/cascadeinference
Author: Eli Butters
Author-email: elibutters@outlook.com
License: MIT
Classifier: Programming Language :: Python :: 3
Classifier: Operating System :: OS Independent
Requires-Python: >=3.6
License-File: LICENSE
Requires-Dist: openai
Requires-Dist: requests
Provides-Extra: test
Requires-Dist: pytest; extra == "test"
Requires-Dist: pytest-asyncio; extra == "test"
Requires-Dist: python-dotenv; extra == "test"
Provides-Extra: semantic
Requires-Dist: fastembed; extra == "semantic"
Requires-Dist: scipy; extra == "semantic"
Dynamic: author
Dynamic: author-email
Dynamic: classifier
Dynamic: description
Dynamic: description-content-type
Dynamic: home-page
Dynamic: license
Dynamic: license-file
Dynamic: provides-extra
Dynamic: requires-dist
Dynamic: requires-python
Dynamic: summary
